quantrabyte/__init__.cpython-311-x86_64-linux-gnu.so
quantrabyte/__init__.py
quantrabyte/factorpy/__init__.cpython-311-x86_64-linux-gnu.so
quantrabyte/factorpy/cloned_factor.cpython-311-x86_64-linux-gnu.so
quantrabyte/factorpy/data_nodes/__init__.cpython-311-x86_64-linux-gnu.so
quantrabyte/factorpy/data_nodes/agg_trades.cpython-311-x86_64-linux-gnu.so
quantrabyte/factorpy/data_nodes/bid_ask_spread.cpython-311-x86_64-linux-gnu.so
quantrabyte/factorpy/data_nodes/consts.cpython-311-x86_64-linux-gnu.so
quantrabyte/factorpy/data_nodes/data_checker_nodes/__init__.cpython-311-x86_64-linux-gnu.so
quantrabyte/factorpy/data_nodes/data_checker_nodes/crypto_missing_mkt_data_checker.cpython-311-x86_64-linux-gnu.so
quantrabyte/factorpy/data_nodes/data_clusters.cpython-311-x86_64-linux-gnu.so
quantrabyte/factorpy/data_nodes/exceptions.cpython-311-x86_64-linux-gnu.so
quantrabyte/factorpy/data_nodes/liquidation_volume.cpython-311-x86_64-linux-gnu.so
quantrabyte/factorpy/data_nodes/mid_prc.cpython-311-x86_64-linux-gnu.so
quantrabyte/factorpy/data_nodes/mkt_data_node.cpython-311-x86_64-linux-gnu.so
quantrabyte/factorpy/data_nodes/resampled_kline.cpython-311-x86_64-linux-gnu.so
quantrabyte/factorpy/data_nodes/total_volume_node.cpython-311-x86_64-linux-gnu.so
quantrabyte/factorpy/factor_cluster.cpython-311-x86_64-linux-gnu.so
quantrabyte/factorpy/factor_manager.cpython-311-x86_64-linux-gnu.so
quantrabyte/factorpy/factor_node.cpython-311-x86_64-linux-gnu.so
quantrabyte/factorpy/test/full_tree_node.cpython-311-x86_64-linux-gnu.so
quantrabyte/factorpy/test/test_tranverse.cpython-311-x86_64-linux-gnu.so
quantrabyte/factorpy/tutorial/__init__.cpython-311-x86_64-linux-gnu.so
quantrabyte/factorpy/tutorial/generate_factor_example.cpython-311-x86_64-linux-gnu.so
quantrabyte/factorpy/tutorial/operators_example.cpython-311-x86_64-linux-gnu.so
quantrabyte/factorpy/tutorial/run_fastbacktest.cpython-311-x86_64-linux-gnu.so
quantrabyte/pyramid_data/__init__.cpython-311-x86_64-linux-gnu.so
quantrabyte-1.3.5.dist-info/METADATA
quantrabyte-1.3.5.dist-info/WHEEL
quantrabyte-1.3.5.dist-info/RECORD
