Metadata-Version: 2.1
Name: quantrabyte
Version: 1.3.5
Summary: 
Author: stark.y
Author-email: ywiscat@gmail.com
Requires-Python: ==3.11.5
Classifier: Programming Language :: Python :: 3
Requires-Dist: apscheduler (>=3.10.4,<4.0.0)
Requires-Dist: cython (==3.0.0)
Requires-Dist: fasteners (==0.19)
Requires-Dist: loguru (==0.7.2)
Requires-Dist: matplotlib (==3.7.2)
Requires-Dist: minio (>=7.2.7,<8.0.0)
Requires-Dist: networkx (==3.1)
Requires-Dist: numpy (==1.24.3)
Requires-Dist: pandas (==2.0.3)
Requires-Dist: prompt-toolkit (>=3.0.48,<4.0.0)
Requires-Dist: psutil (==5.9.5)
Requires-Dist: pyarrow (==15.0.0)
Requires-Dist: pytz (==2023.3.post1)
Requires-Dist: ray (==2.10.0)
Requires-Dist: redis (>=5.0.8,<6.0.0)
Requires-Dist: setuptools (==68.2.2)
Requires-Dist: sigpy (==0.1.26)
Requires-Dist: tardis-dev (>=2.0.0a13,<3.0.0)
Requires-Dist: tqdm (==4.66.2)
